{
  "db_name": "SQLite",
  "query": "SELECT id, domain, cert_pem, key_pem FROM certificates WHERE expires_at > datetime('now')",
  "describe": {
    "columns": [
      {
        "name": "id",
        "ordinal": 0,
        "type_info": "Text"
      },
      {
        "name": "domain",
        "ordinal": 1,
        "type_info": "Text"
      },
      {
        "name": "cert_pem",
        "ordinal": 2,
        "type_info": "Text"
      },
      {
        "name": "key_pem",
        "ordinal": 3,
        "type_info": "Text"
      }
    ],
    "parameters": {
      "Right": 0
    },
    "nullable": [
      true,
      false,
      false,
      false
    ]
  },
  "hash": "d0ef6588e10f45cfd897da2c4d953393fec3b0ec8831195f95ef2cacfddce48c"
}
